cr_kyoushi/dataset/__init__.py
cr_kyoushi/dataset/__main__.py
cr_kyoushi/dataset/cli.py
cr_kyoushi/dataset/config.py
cr_kyoushi/dataset/elasticsearch.py
cr_kyoushi/dataset/files/__init__.py
cr_kyoushi/dataset/files/jvm.options
cr_kyoushi/dataset/files/log4j2.properties
cr_kyoushi/dataset/labels.py
cr_kyoushi/dataset/parser.py
cr_kyoushi/dataset/pcap.py
cr_kyoushi/dataset/processors.py
cr_kyoushi/dataset/sample.py
cr_kyoushi/dataset/templates/ecs-template.json.j2
cr_kyoushi/dataset/templates/input.conf.j2
cr_kyoushi/dataset/templates/legacy-ecs-template.json.j2
cr_kyoushi/dataset/templates/logstash.yml.j2
cr_kyoushi/dataset/templates/output.conf.j2
cr_kyoushi/dataset/templates/pipelines.yml.j2
cr_kyoushi/dataset/templates/pre_process.conf.j2
cr_kyoushi/dataset/templates.py
cr_kyoushi/dataset/utils.py
kyoushi_dataset-0.2.1.dist-info/entry_points.txt
kyoushi_dataset-0.2.1.dist-info/LICENSE
kyoushi_dataset-0.2.1.dist-info/WHEEL
kyoushi_dataset-0.2.1.dist-info/METADATA
kyoushi_dataset-0.2.1.dist-info/RECORD
