Metadata-Version: 2.1
Name: kyoushi-dataset
Version: 0.2.1
Summary: 
Home-page: https://github.com/ait-aecid/kyoushi-dataset
License: MIT
Author: Maximilian Frank
Author-email: maximilian.frank@ait.ac.at
Requires-Python: >=3.7,<4.0
Classifier: License :: OSI Approved :: MIT License
Classifier: Programming Language :: Python :: 3
Classifier: Programming Language :: Python :: 3.10
Classifier: Programming Language :: Python :: 3.7
Classifier: Programming Language :: Python :: 3.8
Classifier: Programming Language :: Python :: 3.9
Requires-Dist: Jinja2 (>=2.11.3,<3.0.0)
Requires-Dist: aiohttp (>=3.7.4,<4.0.0)
Requires-Dist: certifi (>=2020.12.5,<2021.0.0)
Requires-Dist: click (>=7.1.2,<8.0.0)
Requires-Dist: elasticsearch (>=7.12.0,<8.0.0)
Requires-Dist: elasticsearch-dsl (>=7.3.0,<8.0.0)
Requires-Dist: livereload (>=2.6.3,<3.0.0)
Requires-Dist: pydantic (>=1.8.1,<2.0.0)
Requires-Dist: pyshark (>=0.4.3,<0.5.0)
Requires-Dist: ruamel.yaml (>=0.17.2,<0.18.0)
Requires-Dist: ujson (>=4.2.0,<5.0.0)
Project-URL: Repository, https://github.com/ait-aecid/kyoushi-dataset
